LICENSE
MANIFEST.in
README.rst
setup.py
closable_admin_filter/__init__.py
closable_admin_filter/mixins.py
closable_admin_filter/static/admin/css/closable_admin_filter.css
closable_admin_filter/static/admin/js/closable_admin_filter.js
django_closable_admin_filter.egg-info/PKG-INFO
django_closable_admin_filter.egg-info/SOURCES.txt
django_closable_admin_filter.egg-info/dependency_links.txt
django_closable_admin_filter.egg-info/top_level.txt