Metadata-Version: 1.1
Name: django-closable-admin-filter
Version: 0.1.0
Summary: A simple Django app to add hide/show ability to the filter in Django admin.
Home-page: https://github.com/eternalfame/django-closable_admin_filter
Author: Vyacheslav Sukhenko
Author-email: eternalfame@mail.ru
License: MIT License
Platform: UNKNOWN
Classifier: Environment :: Web Environment
Classifier: Framework :: Django
Classifier: Intended Audience :: Developers
Classifier: License :: OSI Approved :: MIT License
Classifier: Operating System :: OS Independent
Classifier: Programming Language :: Python
Classifier: Topic :: Internet :: WWW/HTTP
Classifier: Topic :: Internet :: WWW/HTTP :: Dynamic Content
